{
  "Id": "silenced_tmp",
  "WeaponData": {
    "Name": "Silenced TMP",
    "Damage": 0.15,
    "UseDelay": 0.07,
    "MaxHandRangeMultiplier": 0.8,
    "AdditionalComponents": null,
    "EnsureSystems": null,
    "ThrowableDamage": 15.0,
    "ThrowableHeavy": false,
    "ThrowableSharpBoxes": [],
    "WeaponType": "Firearm",
    "BulletsPerShot": 1,
    "RoundsPerMagazine": 30,
    "BurstFireCount": 0,
    "Accuracy": 1.0,
    "Recoil": 0.2,
    "RotationalRecoilIntensity": 0.5,
    "RecoilHandling": 1.0,
    "Automatic": true,
    "ShootSounds": [
      "sounds/firearms/sup_1.wav"
    ],
    "CanBulletsBeDeflected": true,
    "EjectionParticle": "Small",
    "CasingSize": 1.0,
    "IsPumpAction": false,
    "Range": 400.0,
    "CanDeflectBullets": false,
    "SpecialMelee": false,
    "MeleeDamageType": "Firearm",
    "MeleeSize": "Medium"
  },
  "BaseTexture": "textures/weapons/silenced_tmp/base.png",
  "HoldForGrip": false,
  "HoldStockHandPose": false,
  "BarrelEndPoint": {
    "X": 239.70082,
    "Y": 74.95678
  },
  "CasingEjectionPoint": {
    "X": -152.31165,
    "Y": 84.300705
  },
  "HoldPoints": [
    {
      "X": 141.42154,
      "Y": -24.105389
    }
  ],
  "AnimatedParts": null,
  "OnFloorAngle": 0.0
}